LICENSE
cachedict/__init__.py
cachedict/py.typed
cachedict-0.0.6.1.dist-info/LICENSE
cachedict-0.0.6.1.dist-info/METADATA
cachedict-0.0.6.1.dist-info/WHEEL
cachedict-0.0.6.1.dist-info/RECORD
